Cell_BLAST/__init__.py
Cell_BLAST/blast.py
Cell_BLAST/config.py
Cell_BLAST/data.py
Cell_BLAST/directi.py
Cell_BLAST/latent.py
Cell_BLAST/metrics.py
Cell_BLAST/prob.py
Cell_BLAST/rebuild.py
Cell_BLAST/rmbatch.py
Cell_BLAST/utils.py
Cell_BLAST/weighting.py
cell_blast-0.5.1.dist-info/LICENSE
cell_blast-0.5.1.dist-info/WHEEL
cell_blast-0.5.1.dist-info/METADATA
cell_blast-0.5.1.dist-info/RECORD
