Metadata-Version: 2.1
Name: Cell_BLAST
Version: 0.5.1
Summary: Single-cell transcriptome querying tool
Keywords: bioinformatics,deep-learning,single-cell
Author-email: Zhi-Jie Cao <caozj@mail.cbi.pku.edu.cn>, Runwei Lu <lurw2000@126.com>
Requires-Python: >=3.6
Classifier: Intended Audience :: Science/Research
Classifier: License :: OSI Approved :: MIT License
Classifier: Natural Language :: English
Classifier: Operating System :: MacOS :: MacOS X
Classifier: Operating System :: POSIX :: Linux
Classifier: Programming Language :: Python :: 3
Classifier: Programming Language :: Python :: 3.6
Classifier: Programming Language :: Python :: 3.7
Classifier: Programming Language :: Python :: 3.8
Classifier: Programming Language :: Python :: 3.9
Classifier: Topic :: Scientific/Engineering :: Bio-Informatics
Requires-Dist: numba>=0.39.0
Requires-Dist: scipy>=1.0.0
Requires-Dist: joblib>=0.12.0
Requires-Dist: scikit-learn>=0.17.0
Requires-Dist: tqdm>=4.12.0
Requires-Dist: pandas>=0.21.0
Requires-Dist: h5py>=2.7.0
Requires-Dist: igraph>=0.7.1
Requires-Dist: pronto>=0.10.2,<=0.12.2
Requires-Dist: seaborn>=0.9.0
Requires-Dist: umap-learn>=0.2.1
Requires-Dist: anndata>=0.6.14
Requires-Dist: loompy>=2.0.6
Requires-Dist: statsmodels>=0.8.0
Requires-Dist: plotly>=5.8.2
Requires-Dist: torch>=1.7.1
Requires-Dist: tensorboard>=2.9.1
Requires-Dist: scanpy>=1.9.0
Requires-Dist: leidenalg>=0.8.10
Requires-Dist: pynvml>=8.0.1
Requires-Dist: sphinx<7 ; extra == "doc"
Requires-Dist: sphinx-autodoc-typehints ; extra == "doc"
Requires-Dist: sphinx-copybutton ; extra == "doc"
Requires-Dist: nbsphinx ; extra == "doc"
Requires-Dist: sphinx-rtd-theme ; extra == "doc"
Requires-Dist: ipython ; extra == "doc"
Requires-Dist: jinja2 ; extra == "doc"
Requires-Dist: autodocsumm ; extra == "doc"
Project-URL: Github, https://github.com/gao-lab/Cell_BLAST
Provides-Extra: doc
